CHANGELOG.md
MANIFEST.in
README.md
setup.cfg
setup.py
pip_client_data_python/__init__.py
pip_client_data_python.egg-info/PKG-INFO
pip_client_data_python.egg-info/SOURCES.txt
pip_client_data_python.egg-info/dependency_links.txt
pip_client_data_python.egg-info/requires.txt
pip_client_data_python.egg-info/top_level.txt
pip_client_data_python.egg-info/zip-safe
pip_client_data_python/build/EntitiesClientFactory.py
pip_client_data_python/build/__init__.py
pip_client_data_python/version1/EntitiesCommandableGrpcClientV1.py
pip_client_data_python/version1/EntitiesCommandableHttpClientV1.py
pip_client_data_python/version1/EntitiesCommandableLambdaClientV1.py
pip_client_data_python/version1/EntitiesDirectClientV1.py
pip_client_data_python/version1/EntitiesGrpcClientV1.py
pip_client_data_python/version1/EntitiesGrpcConverter.py
pip_client_data_python/version1/EntitiesLambdaClientV1.py
pip_client_data_python/version1/EntitiesMockClientV1.py
pip_client_data_python/version1/EntitiesNullClientV1.py
pip_client_data_python/version1/EntitiesRestClientV1.py
pip_client_data_python/version1/EntityTypeV1.py
pip_client_data_python/version1/EntityV1.py
pip_client_data_python/version1/EntityV1Schema.py
pip_client_data_python/version1/IEntitiesClientV1.py
pip_client_data_python/version1/RandomEntityV1.py
pip_client_data_python/version1/__init__.py
test/version1/EntitiesClientV1Fixture.py
test/version1/__init__.py
test/version1/test_EntitiesCommandableGrpcClientV1.py
test/version1/test_EntitiesCommandableHttpClientV1.py
test/version1/test_EntitiesCommandableLambdaClientV1.py
test/version1/test_EntitiesDirectClientV1.py
test/version1/test_EntitiesGrpcClientV1.py
test/version1/test_EntitiesLambdaClientV1.py
test/version1/test_EntitiesMockClientV1.py
test/version1/test_EntitiesRestClientV1.py